alibabacloud_imageenhan20190930_test/__init__.py
alibabacloud_imageenhan20190930_test/client.py
alibabacloud_imageenhan20190930_test/models.py
alibabacloud_imageenhan20190930_test-1.0.0.dist-info/LICENSE
alibabacloud_imageenhan20190930_test-1.0.0.dist-info/METADATA
alibabacloud_imageenhan20190930_test-1.0.0.dist-info/WHEEL
alibabacloud_imageenhan20190930_test-1.0.0.dist-info/top_level.txt
alibabacloud_imageenhan20190930_test-1.0.0.dist-info/RECORD
